custom_serializer/__init__.py
custom_serializer/custom_serializer.py
custom_serializer/serializer_factory.py
custom_serializer/encoder/__init__.py
custom_serializer/encoder/constants.py
custom_serializer/encoder/encoder.py
custom_serializer/serializers/__init__.py
custom_serializer/serializers/json_serializer.py
custom_serializer/serializers/xml_serializer.py
dashadmdv_custom_serializer-0.3.0.dist-info/METADATA
dashadmdv_custom_serializer-0.3.0.dist-info/WHEEL
dashadmdv_custom_serializer-0.3.0.dist-info/top_level.txt
dashadmdv_custom_serializer-0.3.0.dist-info/RECORD
