Metadata-Version: 2.1
Name: dashadmdv-custom-serializer
Version: 0.3.0
Summary: My lab for uni
Author: dashadmdv
License: MIT
